kapp/__init__.py
kapp/cli.py
kapp/kapp.py
kapp-0.0.1.dist-info/METADATA
kapp-0.0.1.dist-info/RECORD
kapp-0.0.1.dist-info/WHEEL
kapp-0.0.1.dist-info/entry_points.txt
kapp-0.0.1.dist-info/top_level.txt
