Metadata-Version: 2.1
Name: kapp
Version: 0.0.1
Summary: Deploy and manage SSL-supported web apps on Kubernetes clusters.
Home-page: https://github.com/snormore/kapp/
Author: Steven Normore
Author-email: steven@normore.me
License: UNKNOWN
Platform: UNKNOWN
Requires-Dist: click
Requires-Dist: shell
